models/__init__.py
models/bootstrap.py
models/cluster.py
models/controllers/__init__.py
models/controllers/cluster_controller.py
models/controllers/subscriber_controller.py
models/customer.py
models/datastore/__init__.py
models/datastore/cluster_datastore.py
models/dynamodb.py
models/globals/__init__.py
models/globals/constants.py
models/logs.py
models/repositories.py
stratio_models-0.2.0.dev18.dist-info/METADATA
stratio_models-0.2.0.dev18.dist-info/WHEEL
stratio_models-0.2.0.dev18.dist-info/RECORD
