Metadata-Version: 2.1
Name: stratio-models
Version: 0.2.0.dev18
Summary: Shared models for AWS Marketplace
Home-page: https://github.com/Stratio/aws-marketplace-models
License: MIT
Author: Stratio
Author-email: platform@stratio.com
Requires-Python: >=3.12,<4.0
Classifier: License :: OSI Approved :: MIT License
Classifier: Programming Language :: Python :: 3
Classifier: Programming Language :: Python :: 3.12
Classifier: Programming Language :: Python :: 3.13
Requires-Dist: pydantic (==2.10.3)
